[
  {
    "id": "002bb485-f3e8-413b-b134-dd32e25181dd",
    "title": "abcd",
    "author": "asdsd",
    "category": "Fiction",
    "condition": "Good- Minor wear",
    "description": "abcd",
    "price": 399,
    "donatedBy": "abc",
    "donorEmail": "abc@gmail.com",
    "donorPhone": "123",
    "location": "Jamnagar, Gujarat",
    "dateAdded": "2025-08-21T15:40:02.023Z",
    "status": "available",
    "image": null
  },
  {
    "id": "c6349cc2-4561-4b90-aae5-71b4a31a53e3",
    "title": "sample1",
    "author": "asdsd",
    "category": "Biography",
    "condition": "Poor- Heavily used but readable",
    "description": "",
    "donatedBy": "h",
    "donorEmail": "h@h.com",
    "donorPhone": "1234",
    "location": "Jamnagar, Gujarat",
    "dateAdded": "2025-09-22T09:45:50.291Z",
    "status": "available",
    "book_issued": "Yes",
    "image": null
  },
  {
    "id": "328c43b7-2fc2-4839-9661-a29567b1de13",
    "title": "sample2",
    "author": "hsjk",
    "category": "Fiction",
    "condition": "Excellent- Like new",
    "description": "",
    "donatedBy": "h",
    "donorEmail": "h@h.com",
    "donorPhone": "1234",
    "location": "Jamnagar, Gujarat",
    "dateAdded": "2025-09-22T09:46:20.793Z",
    "status": "available",
    "book_issued": "Yes",
    "image": null
  },
  {
    "id": "fe7a681a-ad4e-4774-9fcf-a0845448946c",
    "title": "sample3",
    "author": "Sudha Murty",
    "category": "Non fiction",
    "condition": "Fair- some wear and tear",
    "description": "",
    "donatedBy": "h",
    "donorEmail": "h@h.com",
    "donorPhone": "1234",
    "location": "Jamnagar, Gujarat",
    "dateAdded": "2025-09-22T09:46:48.259Z",
    "status": "available",
    "book_issued": "Yes",
    "image": null
  },
  {
    "id": "b92a28fe-2078-47a0-87f2-4565171b9cf2",
    "title": "sample4",
    "author": "Sudha Murty",
    "category": "Non fiction",
    "condition": "Excellent- Like new",
    "description": "",
    "donatedBy": "h",
    "donorEmail": "h@h.com",
    "donorPhone": "1234",
    "location": "Jamnagar, Gujarat",
    "dateAdded": "2025-09-22T09:47:12.402Z",
    "status": "available",
    "book_issued": "Yes",
    "image": null
  }
]